Workbook

Sheet Employee_Query_Data
A1: Ticket ID | B1: Employee ID | C1: Employee Name | D1: Region | E1: Query Channel | F1: Query Type | G1: Query Description | H1: Priority | I1: Date Raised | J1: Status | K1: Assigned Team | L1: First Response Time (hrs) | M1: Resolution Time (hrs) | N1: Escalation Required | O1: Customer Satisfaction | P1: Final Resolution
A2: TKT-1001 | B2: EMP93810 | C2: Sophie Sharma | D2: UK | E2: Call | F2: Payroll | G2: March pay slip shows incorrect gross amount | H2: Medium | I2: 45572 | J2: Open | K2: Payroll Ops | L2: 4.5 | M2: 9.2 | N2: No | O2: Satisfied | P2: Verified payroll cycle and informed employee of bank processing delay
A3: TKT-1002 | B3: EMP83563 | C3: David Desai | D3: UK | E3: Email | F3: Leave Balance | G3: Leave taken showing as absent in attendance records | H3: Low | I3: 45296 | J3: Resolved | K3: HR Shared Services | L3: 7.2 | M3: 54.4 | N3: No | O3: Satisfied | P3: Leave record reconciled; system refreshed and confirmed
A4: TKT-1003 | B4: EMP23396 | C4: Mohammed Taylor | D4: India | E4: Webform | F4: Time & Expense | G4: Expense claim reimbursement delayed beyond 30 days | H4: Medium | I4: 45567 | J4: In Progress | K4: Finance Ops | L4: 7.5 | M4: 11.2 | N4: No | O4: Neutral | P4: Travel allowance verified and credited in next payroll
A5: TKT-1004 | B5: EMP85674 | C5: David Desai | D5: India | E5: Chat | F5: Login Access | G5: Account locked after multiple failed login attempts | H5: High | I5: 45344 | J5: Resolved | K5: IT Helpdesk | L5: 2.1 | M5: 20.7 | N5: No | O5: Satisfied | P5: VPN access reinstated after manager authorisation received
A6: TKT-1005 | B6: EMP99593 | C6: Charlotte Khan | D6: UK | E6: Call | F6: Login Access | G6: Two-factor authentication code not received on email | H6: Medium | I6: 45431 | J6: Escalated | K6: IT Helpdesk | L6: 5.8 | M6: 30.3 | N6: Yes | O6: Neutral | P6: Reset portal access and confirmed successful login with employee
A7: TKT-1006 | B7: EMP40021 | C7: Henry Patel | D7: APAC | E7: Email | F7: Payroll | G7: Payroll on hold due to missing bank details update | H7: High | I7: 45454 | J7: In Progress | K7: Payroll Ops | L7: 2.2 | M7: 21.7 | N7: No | O7: Satisfied | P7: Escalated to payroll ops team; updated OT calculation and closed
A8: TKT-1007 | B8: EMP42325 | C8: Divya Thomas | D8: US | E8: Chat | F8: Benefits | G8: Parental benefit enrollment deadline query | H8: Medium | I8: 45405 | J8: Escalated | K8: Benefits Team | L8: 2.8 | M8: 27.7 | N8: Yes | O8: Neutral | P8: Insurance card raised with provider; delivery expected in 5 days
A9: TKT-1008 | B9: EMP30033 | C9: Charlotte Singh | D9: UK | E9: Email | F9: Payroll | G9: Arrears payment from January still not received | H9: Medium | I9: 45532 | J9: Resolved | K9: Payroll Ops | L9: 7.8 | M9: 42.4 | N9: Yes | O9: Neutral | P9: Account details updated; payment reprocessed within 48 hours
A10: TKT-1009 | B10: EMP44973 | C10: William Iyer | D10: India | E10: Call | F10: Payroll | G10: Salary not credited for March payroll run | H10: High | I10: 45427 | J10: Escalated | K10: Payroll Ops | L10: 3.2 | M10: 14.2 | N10: Yes | O10: Satisfied | P10: Regenerated pay slip and shared via secure portal link
A11: TKT-1010 | B11: EMP93748 | C11: Meera Jackson | D11: India | E11: Email | F11: Payroll | G11: Last month's salary credited to wrong account | H11: High | I11: 45599 | J11: Resolved | K11: Payroll Ops | L11: 0.6 | M11: 22.6 | N11: No | O11: Dissatisfied | P11: Regenerated pay slip and shared via secure portal link
A12: TKT-1011 | B12: EMP41385 | C12: Priya Gupta | D12: APAC | E12: Voicemail | F12: Payroll | G12: Bonus amount missing from March salary statement | H12: High | I12: 45565 | J12: Resolved | K12: Payroll Ops | L12: 0.9 | M12: 13.5 | N12: No | O12: Satisfied | P12: Bank details verified and updated; payroll released next cycle
A13: TKT-1012 | B13: EMP65461 | C13: David Moore | D13: US | E13: Chat | F13: Leave Balance | G13: Maternity leave balance not applied correctly | H13: Medium | I13: 45636 | J13: Resolved | K13: HR Shared Services | L13: 4.6 | M13: 28.7 | N13: Yes | O13: Satisfied | P13: Leave record reconciled; system refreshed and confirmed
... A101: TKT-1100 | B101: EMP20682 | C101: Fatima Martin | D101: India | E101: Email | F101: Attendance Issue | G101: Attendance regularisation request not processed | H101: Low | I101: 45336 | J101: Resolved | K101: Attendance Desk | L101: 11.5 | M101: 81 | N101: No | O101: Neutral | P101: Shift schedule corrected; attendance recalculated accurately

Sheet Resolution_Log
A1: Ticket ID | B1: Query Type | C1: Root Cause | D1: Action Taken | E1: Escalated To | F1: Resolution Outcome | G1: TAT Met (Yes/No)
A2: TKT-1012 | B2: Leave Balance | C2: Carry-forward rule not applied | D2: Checked attendance log | E2: IT Helpdesk | F2: Resolved - no further action needed | G2: Yes
A3: TKT-1083 | B3: Leave Balance | C3: Annual reset not triggered | D3: Corrected leave entry | E3: HR Operations | F3: Closed after employee confirmation | G3: Yes
A4: TKT-1086 | B4: Benefits | C4: Eligibility rule error | D4: Closed ticket after confirmation | E4: Payroll Team | F4: Resolved - no further action needed | G4: Yes
A5: TKT-1055 | B5: Leave Balance | C5: Incorrect leave entry | D5: Corrected leave entry | E5: N/A | F5: Resolved and closed | G5: Yes
A6: TKT-1066 | B6: Policy Clarification | C6: Ambiguous policy language | D6: Shared policy document via email | E6: N/A | F6: Closed after employee confirmation | G6: Yes
A7: TKT-1047 | B7: Payroll | C7: System sync issue | D7: Checked bank details and payment logs | E7: N/A | F7: Closed after employee confirmation | G7: Yes
A8: TKT-1003 | B8: Time & Expense | C8: Missing receipts | D8: Checked finance reimbursement status | E8: N/A | F8: Closed after employee confirmation | G8: Yes
A9: TKT-1095 | B9: Login Access | C9: OTP delivery failure | D9: Verified employee identity | E9: N/A | F9: Closed after employee confirmation | G9: Yes
A10: TKT-1040 | B10: Benefits | C10: Enrollment not submitted | D10: Shared resolution ETA with employee | E10: N/A | F10: Resolved - no further action needed | G10: Yes
A11: TKT-1024 | B11: Login Access | C11: OTP delivery failure | D11: Reset portal password | E11: N/A | F11: Closed after employee confirmation | G11: Yes
A12: TKT-1028 | B12: Policy Clarification | C12: Policy document not accessible | D12: Shared policy document via email | E12: N/A | F12: Escalated and closed | G12: Yes
... A61: TKT-1034 | B61: Payroll | C61: Incorrect tax bracket applied | D61: Raised correction ticket with payroll team | E61: N/A | F61: Pending verification | G61: Yes

Sheet SOP_Guide
A1: Standard Operating Procedures (SOP) — CIC Query Resolution
A2: Query Type | B2: Step 1 | C2: Step 2 | D2: Step 3 | E2: Step 4 | F2: Step 5
A3: Payroll | B3: Verify employee ID and payroll period | C3: Check payroll cycle run status in system | D3: Validate bank account and payment details | E3: Escalate to payroll ops if payment failed or delayed | F3: Inform employee of resolution and close ticket
A4: Leave Balance | B4: Check employee's leave policy and entitlement | C4: Review attendance and leave entries in HRMS | D4: Identify and correct any mismatch in records | E4: Confirm updated leave balance with employee | F4: Close query after employee acknowledgement
A5: Benefits | B5: Check employee's enrollment status in benefits portal | C5: Verify eligibility based on grade and tenure | D5: Review policy effective dates and plan details | E5: Escalate to benefits team if correction needed | F5: Share resolution update and close ticket
A6: Time & Expense | B6: Verify expense claim details and receipts submitted | C6: Check finance reimbursement processing status | D6: Guide employee to resubmit with correct documents if rejected | E6: Escalate to finance ops for delayed reimbursements | F6: Confirm payment receipt and close ticket
A7: Login Access | B7: Verify employee identity via employee ID and email | C7: Attempt password reset or account unlock | D7: Escalate to IT helpdesk if issue persists beyond L1 | E7: Confirm new access credentials work correctly | F7: Log resolution and close ticket
A8: Policy Clarification | B8: Identify the specific policy area in question | C8: Review the relevant HR policy document | D8: Clarify policy with HR compliance or HR BP if needed | E8: Share the policy document and explanation with employee | F8: Close ticket after confirming employee understanding
A9: Attendance Issue | B9: Retrieve attendance records from HRMS or biometric system | C9: Cross-check with manager approvals and shift schedule | D9: Correct attendance entry with appropriate approvals | E9: Escalate to IT if system sync or biometric data missing | F9: Confirm correction with employee and close query

Sheet Dashboard
A1: 📊 Customer Query Resolution — Dashboard
A3: Total Tickets | C3: Resolved Tickets | E3: Escalated Tickets | G3: Avg Resolution (hrs) | I3: High Priority Tickets | K3: Satisfaction Rate (%)
A4: =COUNTA(Employee_Query_Data!A2:A101) -> 100 | C4: =COUNTIF(Employee_Query_Data!J:J,"Resolved") -> 55 | E4: =COUNTIF(Employee_Query_Data!N:N,"Yes") -> 27 | G4: =ROUND(AVERAGE(Employee_Query_Data!M2:M101),1) -> 29.8 | I4: =COUNTIF(Employee_Query_Data!H:H,"High") -> 28 | K4: =ROUND(COUNTIF(Employee_Query_Data!O:O,"Satisfied")/COUNTA(Employee_Query_Data!O2:O101)*100,1) -> 48
A7: Tickets by Query Type | D7: Tickets by Channel | G7: Status Distribution
A8: Query Type | B8: Count | D8: Channel | E8: Count | G8: Status | H8: Count
A9: Payroll | B9: =COUNTIF(Employee_Query_Data!F:F,A9) -> 22 | D9: Call | E9: =COUNTIF(Employee_Query_Data!E:E,D9) -> 32 | G9: Open | H9: =COUNTIF(Employee_Query_Data!J:J,G9) -> 13
A10: Leave Balance | B10: =COUNTIF(Employee_Query_Data!F:F,A10) -> 15 | D10: Email | E10: =COUNTIF(Employee_Query_Data!E:E,D10) -> 30 | G10: In Progress | H10: =COUNTIF(Employee_Query_Data!J:J,G10) -> 14
A11: Benefits | B11: =COUNTIF(Employee_Query_Data!F:F,A11) -> 12 | D11: Chat | E11: =COUNTIF(Employee_Query_Data!E:E,D11) -> 20 | G11: Resolved | H11: =COUNTIF(Employee_Query_Data!J:J,G11) -> 55
A12: Time & Expense | B12: =COUNTIF(Employee_Query_Data!F:F,A12) -> 18 | D12: Webform | E12: =COUNTIF(Employee_Query_Data!E:E,D12) -> 10 | G12: Escalated | H12: =COUNTIF(Employee_Query_Data!J:J,G12) -> 18
A13: Login Access | B13: =COUNTIF(Employee_Query_Data!F:F,A13) -> 11 | D13: Voicemail | E13: =COUNTIF(Employee_Query_Data!E:E,D13) -> 8
A14: Policy Clarification | B14: =COUNTIF(Employee_Query_Data!F:F,A14) -> 13
A15: Attendance Issue | B15: =COUNTIF(Employee_Query_Data!F:F,A15) -> 9
A17: Region-wise Ticket Volume | D17: Escalations by Query Type | G17: Avg Resolution Time by Query Type (hrs)
A18: Region | B18: Count | D18: Query Type | E18: Escalated | G18: Query Type | H18: Avg Hrs
A19: India | B19: =COUNTIF(Employee_Query_Data!D:D,A19) -> 33 | D19: Payroll | E19: =COUNTIFS(Employee_Query_Data!F:F,D19,Employee_Query_Data!N:N,"Yes") -> 8 | G19: Payroll | H19: =IFERROR(ROUND(AVERAGEIF(Employee_Query_Data!F:F,G19,Employee_Query_Data!M:M),1),0) -> 29.1
A20: US | B20: =COUNTIF(Employee_Query_Data!D:D,A20) -> 19 | D20: Leave Balance | E20: =COUNTIFS(Employee_Query_Data!F:F,D20,Employee_Query_Data!N:N,"Yes") -> 4 | G20: Leave Balance | H20: =IFERROR(ROUND(AVERAGEIF(Employee_Query_Data!F:F,G20,Employee_Query_Data!M:M),1),0) -> 31.7
A21: UK | B21: =COUNTIF(Employee_Query_Data!D:D,A21) -> 24 | D21: Benefits | E21: =COUNTIFS(Employee_Query_Data!F:F,D21,Employee_Query_Data!N:N,"Yes") -> 5 | G21: Benefits | H21: =IFERROR(ROUND(AVERAGEIF(Employee_Query_Data!F:F,G21,Employee_Query_Data!M:M),1),0) -> 29.8
A22: APAC | B22: =COUNTIF(Employee_Query_Data!D:D,A22) -> 24 | D22: Time & Expense | E22: =COUNTIFS(Employee_Query_Data!F:F,D22,Employee_Query_Data!N:N,"Yes") -> 5 | G22: Time & Expense | H22: =IFERROR(ROUND(AVERAGEIF(Employee_Query_Data!F:F,G22,Employee_Query_Data!M:M),1),0) -> 25.2
D23: Login Access | E23: =COUNTIFS(Employee_Query_Data!F:F,D23,Employee_Query_Data!N:N,"Yes") -> 1 | G23: Login Access | H23: =IFERROR(ROUND(AVERAGEIF(Employee_Query_Data!F:F,G23,Employee_Query_Data!M:M),1),0) -> 34.6
D24: Policy Clarification | E24: =COUNTIFS(Employee_Query_Data!F:F,D24,Employee_Query_Data!N:N,"Yes") -> 4 | G24: Policy Clarification | H24: =IFERROR(ROUND(AVERAGEIF(Employee_Query_Data!F:F,G24,Employee_Query_Data!M:M),1),0) -> 28.6
D25: Attendance Issue | E25: =COUNTIFS(Employee_Query_Data!F:F,D25,Employee_Query_Data!N:N,"Yes") -> 0 | G25: Attendance Issue | H25: =IFERROR(ROUND(AVERAGEIF(Employee_Query_Data!F:F,G25,Employee_Query_Data!M:M),1),0) -> 33.4
